btool
