Metadata-Version: 2.1
Name: btool
Version: 1.3
Summary: Backtest Tool
Home-page: UNKNOWN
Author: cmwhknz
Author-email: cmwhknz@mail.com
License: UNKNOWN
Platform: UNKNOWN
Classifier: Programming Language :: Python :: 3
Classifier: License :: OSI Approved :: MIT License
Classifier: Operating System :: OS Independent
License-File: LICENSE
